[
  {
    "team_key": "469.l.4114.t.1",
    "team_score": 0.0,
    "team_projected": 168.07,
    "week": 1,
    "opponent_key": "469.l.4114.t.4",
    "opponent_score": 0.0,
    "opponent_projected": 149.62
  },
  {
    "team_key": "469.l.4114.t.4",
    "team_score": 0.0,
    "team_projected": 149.62,
    "week": 1,
    "opponent_key": "469.l.4114.t.1",
    "opponent_score": 0.0,
    "opponent_projected": 168.07
  },
  {
    "team_key": "469.l.4114.t.2",
    "team_score": 0.0,
    "team_projected": 117.51,
    "week": 1,
    "opponent_key": "469.l.4114.t.7",
    "opponent_score": 0.0,
    "opponent_projected": 182.16
  },
  {
    "team_key": "469.l.4114.t.7",
    "team_score": 0.0,
    "team_projected": 182.16,
    "week": 1,
    "opponent_key": "469.l.4114.t.2",
    "opponent_score": 0.0,
    "opponent_projected": 117.51
  },
  {
    "team_key": "469.l.4114.t.3",
    "team_score": 0.0,
    "team_projected": 185.53,
    "week": 1,
    "opponent_key": "469.l.4114.t.6",
    "opponent_score": 0.0,
    "opponent_projected": 137.55
  },
  {
    "team_key": "469.l.4114.t.6",
    "team_score": 0.0,
    "team_projected": 137.55,
    "week": 1,
    "opponent_key": "469.l.4114.t.3",
    "opponent_score": 0.0,
    "opponent_projected": 185.53
  },
  {
    "team_key": "469.l.4114.t.5",
    "team_score": 0.0,
    "team_projected": 131.05,
    "week": 1,
    "opponent_key": "469.l.4114.t.10",
    "opponent_score": 0.0,
    "opponent_projected": 181.99
  },
  {
    "team_key": "469.l.4114.t.10",
    "team_score": 0.0,
    "team_projected": 181.99,
    "week": 1,
    "opponent_key": "469.l.4114.t.5",
    "opponent_score": 0.0,
    "opponent_projected": 131.05
  },
  {
    "team_key": "469.l.4114.t.8",
    "team_score": 0.0,
    "team_projected": 149.96,
    "week": 1,
    "opponent_key": "469.l.4114.t.11",
    "opponent_score": 0.0,
    "opponent_projected": 159.15
  },
  {
    "team_key": "469.l.4114.t.11",
    "team_score": 0.0,
    "team_projected": 159.15,
    "week": 1,
    "opponent_key": "469.l.4114.t.8",
    "opponent_score": 0.0,
    "opponent_projected": 149.96
  },
  {
    "team_key": "469.l.4114.t.9",
    "team_score": 0.0,
    "team_projected": 187.32,
    "week": 1,
    "opponent_key": "469.l.4114.t.12",
    "opponent_score": 0.0,
    "opponent_projected": 121.66
  },
  {
    "team_key": "469.l.4114.t.12",
    "team_score": 0.0,
    "team_projected": 121.66,
    "week": 1,
    "opponent_key": "469.l.4114.t.9",
    "opponent_score": 0.0,
    "opponent_projected": 187.32
  }
]