{
  "date": "2026-07-01",
  "updated": "2026-07-01T10:01:55.057790+00:00",
  "teams_playing": [
    "ARI",
    "ATL",
    "BAL",
    "BOS",
    "CHC",
    "CIN",
    "CLE",
    "COL",
    "CWS",
    "DET",
    "HOU",
    "KC",
    "LAD",
    "MIA",
    "MIL",
    "MIN",
    "NYM",
    "NYY",
    "OAK",
    "PHI",
    "PIT",
    "SD",
    "SF",
    "STL",
    "TB",
    "TEX",
    "TOR",
    "WSH"
  ],
  "game_count": 14,
  "games": [
    {
      "game_pk": 824818,
      "game_date": "2026-07-01T16:35:00Z",
      "status": "Scheduled",
      "home_team": "BAL",
      "away_team": "CWS",
      "home_probable_pitcher": null,
      "away_probable_pitcher": {
        "player_id": 702273,
        "name": "Noah Schultz"
      },
      "home_lineup": [],
      "away_lineup": []
    },
    {
      "game_pk": 824419,
      "game_date": "2026-07-01T17:10:00Z",
      "status": "Scheduled",
      "home_team": "CLE",
      "away_team": "TEX",
      "home_probable_pitcher": {
        "player_id": 676282,
        "name": "Joey Cantillo"
      },
      "away_probable_pitcher": {
        "player_id": 669022,
        "name": "MacKenzie Gore"
      },
      "home_lineup": [],
      "away_lineup": []
    },
    {
      "game_pk": 824740,
      "game_date": "2026-07-01T17:35:00Z",
      "status": "Scheduled",
      "home_team": "BOS",
      "away_team": "WSH",
      "home_probable_pitcher": {
        "player_id": 801139,
        "name": "Payton Tolle"
      },
      "away_probable_pitcher": {
        "player_id": 674841,
        "name": "Andrew Alvarez"
      },
      "home_lineup": [],
      "away_lineup": []
    },
    {
      "game_pk": 823530,
      "game_date": "2026-07-01T17:35:00Z",
      "status": "Scheduled",
      "home_team": "NYY",
      "away_team": "DET",
      "home_probable_pitcher": {
        "player_id": 701542,
        "name": "Will Warren"
      },
      "away_probable_pitcher": {
        "player_id": 675512,
        "name": "Troy Melton"
      },
      "home_lineup": [],
      "away_lineup": []
    },
    {
      "game_pk": 824660,
      "game_date": "2026-07-01T18:20:00Z",
      "status": "Scheduled",
      "home_team": "CHC",
      "away_team": "SD",
      "home_probable_pitcher": {
        "player_id": 607067,
        "name": "Colin Rea"
      },
      "away_probable_pitcher": {
        "player_id": 621111,
        "name": "Walker Buehler"
      },
      "home_lineup": [],
      "away_lineup": []
    },
    {
      "game_pk": 822791,
      "game_date": "2026-07-01T19:07:00Z",
      "status": "Scheduled",
      "home_team": "TOR",
      "away_team": "NYM",
      "home_probable_pitcher": {
        "player_id": 680755,
        "name": "Braydon Fisher"
      },
      "away_probable_pitcher": {
        "player_id": 642547,
        "name": "Freddy Peralta"
      },
      "home_lineup": [],
      "away_lineup": []
    },
    {
      "game_pk": 823446,
      "game_date": "2026-07-01T22:40:00Z",
      "status": "Scheduled",
      "home_team": "PHI",
      "away_team": "PIT",
      "home_probable_pitcher": {
        "player_id": 554430,
        "name": "Zack Wheeler"
      },
      "away_probable_pitcher": {
        "player_id": 694973,
        "name": "Paul Skenes"
      },
      "home_lineup": [],
      "away_lineup": []
    },
    {
      "game_pk": 824905,
      "game_date": "2026-07-01T23:15:00Z",
      "status": "Scheduled",
      "home_team": "ATL",
      "away_team": "STL",
      "home_probable_pitcher": {
        "player_id": 625643,
        "name": "Reynaldo L\u00f3pez"
      },
      "away_probable_pitcher": {
        "player_id": 700241,
        "name": "Michael McGreevy"
      },
      "home_lineup": [],
      "away_lineup": []
    },
    {
      "game_pk": 824094,
      "game_date": "2026-07-01T23:40:00Z",
      "status": "Scheduled",
      "home_team": "KC",
      "away_team": "TB",
      "home_probable_pitcher": {
        "player_id": 607625,
        "name": "Seth Lugo"
      },
      "away_probable_pitcher": {
        "player_id": 663556,
        "name": "Shane McClanahan"
      },
      "home_lineup": [],
      "away_lineup": []
    },
    {
      "game_pk": 824174,
      "game_date": "2026-07-02T00:10:00Z",
      "status": "Scheduled",
      "home_team": "HOU",
      "away_team": "MIN",
      "home_probable_pitcher": {
        "player_id": 837227,
        "name": "Tatsuya Imai"
      },
      "away_probable_pitcher": {
        "player_id": 671737,
        "name": "Taj Bradley"
      },
      "home_lineup": [],
      "away_lineup": []
    },
    {
      "game_pk": 823767,
      "game_date": "2026-07-02T00:10:00Z",
      "status": "Scheduled",
      "home_team": "MIL",
      "away_team": "CIN",
      "home_probable_pitcher": {
        "player_id": 675660,
        "name": "Shane Drohan"
      },
      "away_probable_pitcher": {
        "player_id": 671096,
        "name": "Andrew Abbott"
      },
      "home_lineup": [],
      "away_lineup": []
    },
    {
      "game_pk": 824337,
      "game_date": "2026-07-02T00:40:00Z",
      "status": "Scheduled",
      "home_team": "COL",
      "away_team": "MIA",
      "home_probable_pitcher": {
        "player_id": 607536,
        "name": "Kyle Freeland"
      },
      "away_probable_pitcher": {
        "player_id": 676974,
        "name": "Max Meyer"
      },
      "home_lineup": [],
      "away_lineup": []
    },
    {
      "game_pk": 824985,
      "game_date": "2026-07-02T01:40:00Z",
      "status": "Scheduled",
      "home_team": "OAK",
      "away_team": "LAD",
      "home_probable_pitcher": {
        "player_id": 669372,
        "name": "J.T. Ginn"
      },
      "away_probable_pitcher": null,
      "home_lineup": [],
      "away_lineup": []
    },
    {
      "game_pk": 825064,
      "game_date": "2026-07-02T01:40:00Z",
      "status": "Scheduled",
      "home_team": "ARI",
      "away_team": "SF",
      "home_probable_pitcher": {
        "player_id": 668678,
        "name": "Zac Gallen"
      },
      "away_probable_pitcher": {
        "player_id": 686790,
        "name": "Trevor McDonald"
      },
      "home_lineup": [],
      "away_lineup": []
    }
  ]
}