[
  {
    "team_key": "469.l.4114.t.1",
    "team_score": 116.5,
    "team_projected": 386.82,
    "team_orig_projected": 367.66,
    "week": 11,
    "opponent_key": "469.l.4114.t.6",
    "opponent_score": 60.2,
    "opponent_projected": 301.27
  },
  {
    "team_key": "469.l.4114.t.6",
    "team_score": 60.2,
    "team_projected": 301.27,
    "team_orig_projected": 310.35,
    "week": 11,
    "opponent_key": "469.l.4114.t.1",
    "opponent_score": 116.5,
    "opponent_projected": 386.82
  },
  {
    "team_key": "469.l.4114.t.2",
    "team_score": 120.43,
    "team_projected": 350.33,
    "team_orig_projected": 335.06,
    "week": 11,
    "opponent_key": "469.l.4114.t.3",
    "opponent_score": 67.87,
    "opponent_projected": 369.99
  },
  {
    "team_key": "469.l.4114.t.3",
    "team_score": 67.87,
    "team_projected": 369.99,
    "team_orig_projected": 386.66,
    "week": 11,
    "opponent_key": "469.l.4114.t.2",
    "opponent_score": 120.43,
    "opponent_projected": 350.33
  },
  {
    "team_key": "469.l.4114.t.4",
    "team_score": 84.85,
    "team_projected": 327.43,
    "team_orig_projected": 325.03,
    "week": 11,
    "opponent_key": "469.l.4114.t.12",
    "opponent_score": 83.77,
    "opponent_projected": 326.6
  },
  {
    "team_key": "469.l.4114.t.12",
    "team_score": 83.77,
    "team_projected": 326.6,
    "team_orig_projected": 310.97,
    "week": 11,
    "opponent_key": "469.l.4114.t.4",
    "opponent_score": 84.85,
    "opponent_projected": 327.43
  },
  {
    "team_key": "469.l.4114.t.5",
    "team_score": 74.27,
    "team_projected": 275.85,
    "team_orig_projected": 276.94,
    "week": 11,
    "opponent_key": "469.l.4114.t.7",
    "opponent_score": 59.62,
    "opponent_projected": 336.91
  },
  {
    "team_key": "469.l.4114.t.7",
    "team_score": 59.62,
    "team_projected": 336.91,
    "team_orig_projected": 363.26,
    "week": 11,
    "opponent_key": "469.l.4114.t.5",
    "opponent_score": 74.27,
    "opponent_projected": 275.85
  },
  {
    "team_key": "469.l.4114.t.8",
    "team_score": 63.08,
    "team_projected": 277.01,
    "team_orig_projected": 323.53,
    "week": 11,
    "opponent_key": "469.l.4114.t.9",
    "opponent_score": 82.25,
    "opponent_projected": 340.71
  },
  {
    "team_key": "469.l.4114.t.9",
    "team_score": 82.25,
    "team_projected": 340.71,
    "team_orig_projected": 348.76,
    "week": 11,
    "opponent_key": "469.l.4114.t.8",
    "opponent_score": 63.08,
    "opponent_projected": 277.01
  },
  {
    "team_key": "469.l.4114.t.10",
    "team_score": 52.57,
    "team_projected": 343.43,
    "team_orig_projected": 376.34,
    "week": 11,
    "opponent_key": "469.l.4114.t.11",
    "opponent_score": 59.32,
    "opponent_projected": 299.25
  },
  {
    "team_key": "469.l.4114.t.11",
    "team_score": 59.32,
    "team_projected": 299.25,
    "team_orig_projected": 302.01,
    "week": 11,
    "opponent_key": "469.l.4114.t.10",
    "opponent_score": 52.57,
    "opponent_projected": 343.43
  }
]