[
  {
    "team_key": "469.l.4114.t.1",
    "team_score": 148.97,
    "team_projected": 356.93,
    "team_orig_projected": 352.91,
    "week": 13,
    "opponent_key": "469.l.4114.t.9",
    "opponent_score": 116.5,
    "opponent_projected": 316.86
  },
  {
    "team_key": "469.l.4114.t.9",
    "team_score": 116.5,
    "team_projected": 316.86,
    "team_orig_projected": 366.75,
    "week": 13,
    "opponent_key": "469.l.4114.t.1",
    "opponent_score": 148.97,
    "opponent_projected": 356.93
  },
  {
    "team_key": "469.l.4114.t.2",
    "team_score": 113.53,
    "team_projected": 261.4,
    "team_orig_projected": 275.42,
    "week": 13,
    "opponent_key": "469.l.4114.t.10",
    "opponent_score": 162.75,
    "opponent_projected": 360.29
  },
  {
    "team_key": "469.l.4114.t.10",
    "team_score": 162.75,
    "team_projected": 360.29,
    "team_orig_projected": 368.33,
    "week": 13,
    "opponent_key": "469.l.4114.t.2",
    "opponent_score": 113.53,
    "opponent_projected": 261.4
  },
  {
    "team_key": "469.l.4114.t.3",
    "team_score": 174.58,
    "team_projected": 400.43,
    "team_orig_projected": 398.69,
    "week": 13,
    "opponent_key": "469.l.4114.t.4",
    "opponent_score": 106.34,
    "opponent_projected": 248.36
  },
  {
    "team_key": "469.l.4114.t.4",
    "team_score": 106.34,
    "team_projected": 248.36,
    "team_orig_projected": 249.56,
    "week": 13,
    "opponent_key": "469.l.4114.t.3",
    "opponent_score": 174.58,
    "opponent_projected": 400.43
  },
  {
    "team_key": "469.l.4114.t.5",
    "team_score": 159.85,
    "team_projected": 306.23,
    "team_orig_projected": 304.17,
    "week": 13,
    "opponent_key": "469.l.4114.t.11",
    "opponent_score": 130.07,
    "opponent_projected": 329.24
  },
  {
    "team_key": "469.l.4114.t.11",
    "team_score": 130.07,
    "team_projected": 329.24,
    "team_orig_projected": 319.24,
    "week": 13,
    "opponent_key": "469.l.4114.t.5",
    "opponent_score": 159.85,
    "opponent_projected": 306.23
  },
  {
    "team_key": "469.l.4114.t.6",
    "team_score": 191.45,
    "team_projected": 363.08,
    "team_orig_projected": 330.09,
    "week": 13,
    "opponent_key": "469.l.4114.t.7",
    "opponent_score": 150.95,
    "opponent_projected": 333.18
  },
  {
    "team_key": "469.l.4114.t.7",
    "team_score": 150.95,
    "team_projected": 333.18,
    "team_orig_projected": 336.54,
    "week": 13,
    "opponent_key": "469.l.4114.t.6",
    "opponent_score": 191.45,
    "opponent_projected": 363.08
  },
  {
    "team_key": "469.l.4114.t.8",
    "team_score": 128.72,
    "team_projected": 300.63,
    "team_orig_projected": 296.86,
    "week": 13,
    "opponent_key": "469.l.4114.t.12",
    "opponent_score": 188.63,
    "opponent_projected": 356.42
  },
  {
    "team_key": "469.l.4114.t.12",
    "team_score": 188.63,
    "team_projected": 356.42,
    "team_orig_projected": 297.63,
    "week": 13,
    "opponent_key": "469.l.4114.t.8",
    "opponent_score": 128.72,
    "opponent_projected": 300.63
  }
]